pyanime4k-3.1.0.dist-info/RECORD
pyanime4k-3.1.0.dist-info/WHEEL
pyanime4k-3.1.0.dist-info/top_level.txt
pyanime4k-3.1.0.dist-info/METADATA
pyanime4k-3.1.0.dist-info/licenses/LICENSE
pyanime4k/upscale.py
pyanime4k/__init__.py
pyanime4k/info.py
pyanime4k/pyac/__init__.py
pyanime4k/pyac/pyac.cpython-312-darwin.so
pyanime4k/pyac/pyac/__init__.pyi
pyanime4k/pyac/pyac/core.pyi
pyanime4k/pyac/pyac/specs.pyi
